sumav/__init__.py
sumav/conf.py
sumav/console.py
sumav/dbconnector.py
sumav/schema.sql
sumav/utils.py
sumav/version.py
sumav/graph/__init__.py
sumav/graph/builder.py
sumav/graph/manager.py
sumav/graph/searcher.py
sumav/graph/tests/__init__.py
sumav/graph/tests/test_graph.py
sumav/preprocessing/__init__.py
sumav/preprocessing/base.py
sumav/preprocessing/from_vt_api_v2.py
sumav/preprocessing/from_vt_filefeed.py
sumav/preprocessing/tests/__init__.py
sumav/preprocessing/tests/change_all_gt.tsv
sumav/preprocessing/tests/file-20200526T0831.tar.bz2
sumav/preprocessing/tests/malheurReference_lb.json
sumav/preprocessing/tests/part_change_all_gt.tsv
sumav/preprocessing/tests/part_malheurReference_lb.json
sumav/preprocessing/tests/test_vt.py
sumav/preprocessing/tests/__pycache__/__init__.cpython-36.pyc
sumav/preprocessing/tests/__pycache__/test_vt.cpython-36-pytest-5.4.1.pyc
sumav-1.0.3.dist-info/LICENSE
sumav-1.0.3.dist-info/METADATA
sumav-1.0.3.dist-info/WHEEL
sumav-1.0.3.dist-info/entry_points.txt
sumav-1.0.3.dist-info/top_level.txt
sumav-1.0.3.dist-info/RECORD
