Metadata-Version: 2.1
Name: sumav
Version: 1.0.3
Summary: Sumav is a fully automated labeling tool that assigns each file a family name based on AV labels.
Home-page: https://github.com/bestksw/sumav
Author: Sangwon Kim
Author-email: bestksw@gmail.com
License: Apache 2.0
Keywords: summerize detecion anti-virus software virustotal labeling
Platform: UNKNOWN
Classifier: Programming Language :: Python :: 3
Classifier: Intended Audience :: Developers
Classifier: Intended Audience :: Science/Research
Classifier: Topic :: Scientific/Engineering :: Artificial Intelligence
Requires-Python: >=3.4
Requires-Dist: psycopg2-binary
Requires-Dist: requests
